cosmic_pipeline/__init__.py
cosmic_pipeline/admin.py
cosmic_pipeline/apps.py
cosmic_pipeline/check.py
cosmic_pipeline/choices.py
cosmic_pipeline/constants.py
cosmic_pipeline/exceptions.py
cosmic_pipeline/forms.py
cosmic_pipeline/handler.py
cosmic_pipeline/signals.py
cosmic_pipeline/tests.py
cosmic_pipeline/views.py
cosmic_pipeline/fields/__init__.py
cosmic_pipeline/fields/fields.py
cosmic_pipeline/migrations/0001_initial.py
cosmic_pipeline/migrations/0002_transition_display_name.py
cosmic_pipeline/migrations/0003_transition_post_change_processor.py
cosmic_pipeline/migrations/0004_alter_transition_post_change_processor.py
cosmic_pipeline/migrations/0005_alter_workflow_workflow_model.py
cosmic_pipeline/migrations/0006_restrictrulecondition_metadata_transition_metadata_and_more.py
cosmic_pipeline/migrations/__init__.py
cosmic_pipeline/mixins/__init__.py
cosmic_pipeline/mixins/admin.py
cosmic_pipeline/models/__init__.py
cosmic_pipeline/models/base.py
cosmic_pipeline/models/rules.py
cosmic_pipeline/models/transition.py
cosmic_pipeline/models/transitionstate.py
cosmic_pipeline/models/workflow.py
cosmic_pipeline/utils/__init__.py
cosmic_pipeline/utils/check_restriction_rules.py
cosmic_pipeline/utils/file_names.py
cosmic_pipeline-0.3.1.dist-info/METADATA
cosmic_pipeline-0.3.1.dist-info/WHEEL
cosmic_pipeline-0.3.1.dist-info/top_level.txt
cosmic_pipeline-0.3.1.dist-info/RECORD
