Metadata-Version: 2.1
Name: cosmic_pipeline
Version: 0.3.1
Home-page: https://github.com/Digital-Intel/CosmicPipeline
Author: Digital Intelligence GmbH
Author-email: 
Requires-Python: >=3.6
Requires-Dist: Django >=3.2
Requires-Dist: djangorestframework >=3.14.0
